{
  "nodes": [
    {
      "x": 0.0,
      "y": 54.0
    },
    {
      "x": 90.0,
      "y": 36.0
    },
    {
      "x": 18.0,
      "y": 90.0
    },
    {
      "x": 108.0,
      "y": 0.0
    },
    {
      "x": 0.0,
      "y": 72.0
    },
    {
      "x": 36.0,
      "y": 90.0
    },
    {
      "x": 108.0,
      "y": 54.0
    }
  ],
  "demand": [
    -10.609662554356705,
    -53.14518744188281,
    -36.24515000376049,
    36.32335047176701,
    7.571514809321771,
    26.95923823612642,
    29.14589648278481
  ],
  "pressure": [
    {
      "lb": 40.0,
      "ub": 80.0
    },
    {
      "lb": 40.0,
      "ub": 80.0
    },
    {
      "lb": 40.0,
      "ub": 80.0
    },
    {
      "lb": 40.0,
      "ub": 80.0
    },
    {
      "lb": 40.0,
      "ub": 80.0
    },
    {
      "lb": 40.0,
      "ub": 80.0
    },
    {
      "lb": 40.0,
      "ub": 80.0
    }
  ],
  "diameters": [
    {
      "value": 0.4,
      "cost": 0.68
    },
    {
      "value": 0.8,
      "cost": 1.2
    },
    {
      "value": 1.2,
      "cost": 1.96
    }
  ],
  "ploss_coeff": 0.0003
}
