{
  "nodes": [
    {
      "x": 30.0,
      "y": 96.0
    },
    {
      "x": 24.0,
      "y": 78.0
    },
    {
      "x": 60.0,
      "y": 84.0
    },
    {
      "x": 72.0,
      "y": 48.0
    },
    {
      "x": 0.0,
      "y": 66.0
    }
  ],
  "demand": [
    -100.0,
    20.859011122042467,
    27.695594834325433,
    38.76255900949218,
    12.682835034139913
  ],
  "pressure": [
    {
      "lb": 40.0,
      "ub": 80.0
    },
    {
      "lb": 40.0,
      "ub": 80.0
    },
    {
      "lb": 40.0,
      "ub": 80.0
    },
    {
      "lb": 40.0,
      "ub": 80.0
    },
    {
      "lb": 40.0,
      "ub": 80.0
    }
  ],
  "diameters": [
    {
      "value": 0.4,
      "cost": 0.68
    },
    {
      "value": 0.6,
      "cost": 0.91
    },
    {
      "value": 0.8,
      "cost": 1.2
    },
    {
      "value": 1.0,
      "cost": 1.55
    },
    {
      "value": 1.2,
      "cost": 1.96
    }
  ],
  "ploss_coeff": 0.0003
}
