{
  "nodes": [
    {
      "x": 102.0,
      "y": 66.0
    },
    {
      "x": 78.0,
      "y": 90.0
    },
    {
      "x": 90.0,
      "y": 108.0
    },
    {
      "x": 30.0,
      "y": 18.0
    },
    {
      "x": 6.0,
      "y": 0.0
    },
    {
      "x": 18.0,
      "y": 6.0
    },
    {
      "x": 48.0,
      "y": 18.0
    }
  ],
  "demand": [
    -200.0,
    52.090514445126736,
    22.075073465295787,
    41.71827300158874,
    14.710877866459112,
    21.820052936647286,
    47.58520828488233
  ],
  "pressure": [
    {
      "lb": 40.0,
      "ub": 80.0
    },
    {
      "lb": 40.0,
      "ub": 80.0
    },
    {
      "lb": 40.0,
      "ub": 80.0
    },
    {
      "lb": 40.0,
      "ub": 80.0
    },
    {
      "lb": 40.0,
      "ub": 80.0
    },
    {
      "lb": 40.0,
      "ub": 80.0
    },
    {
      "lb": 40.0,
      "ub": 80.0
    }
  ],
  "diameters": [
    {
      "value": 0.4,
      "cost": 0.68
    },
    {
      "value": 0.8,
      "cost": 1.2
    },
    {
      "value": 1.2,
      "cost": 1.96
    }
  ],
  "ploss_coeff": 0.0003
}
